dremio_provider/__init__.py
dremio_provider/example_dags/__init__.py
dremio_provider/example_dags/example_manage_reflection.py
dremio_provider/hooks/__init__.py
dremio_provider/hooks/dremio.py
dremio_provider/operators/__init__.py
dremio_provider/operators/dremio.py
dremio_provider/sensors/__init__.py
dremio_provider/sensors/dremio.py
dremio_provider/triggers/__init__.py
dremio_provider/triggers/dremio.py
airflow_dremio_provider-0.1.1.dist-info/METADATA
airflow_dremio_provider-0.1.1.dist-info/WHEEL
airflow_dremio_provider-0.1.1.dist-info/entry_points.txt
airflow_dremio_provider-0.1.1.dist-info/licenses/LICENSE
airflow_dremio_provider-0.1.1.dist-info/RECORD
