Metadata-Version: 2.3
Name: airflow-dremio-provider
Version: 0.1.1
Summary: A provider package for managing reflections and executing queries via Dremio.
Project-URL: Homepage, https://github.com/sanchitsreekanth/airflow-provider-dremio
Author-email: Sanchit Sreekanth <sanchitsreekanth@gmail.com>
License-Expression: Apache-2.0
License-File: LICENSE
Keywords: airflow,apache-airflow,dremio,provider
Classifier: Framework :: Apache Airflow
Classifier: Framework :: Apache Airflow :: Provider
Requires-Python: >=3.7
Requires-Dist: apache-airflow-providers-http==4.10.0
Requires-Dist: apache-airflow>=2.6.0
Requires-Dist: requests==2.31.0
